{
    "type": "service_account",
    "project_id": "",
    "private_key_id": "",
    "private_key": "",
    "client_email": "",
    "client_id": "",
    "auth_uri": "",
    "token_uri": "",
    "auth_provider_x509_cert_url": "",
    "client_x509_cert_url": "",
    
    "source_image" : "ubuntu-1804-bionic-v20211021",
    "ssh_username" : "packer",
    "zone"    : "us-central1-a",
    "region"    : "us-central1",
    "machine_type" : "n1-standard-1",
    "image_description": "custom machine image",
    "image_name"       : "packerimage",
    "disk_size" : "10",
    "network" : "packervpc",
    "subnetwork"      : "packersubnet"
}
